senepy/__init__.py
senepy/load_hubs.py
senepy/score_hub.py
senepy/translator.py
senepy/data/5_TMS_HUBS_DICTIONARY_FILTERED.pickle
senepy/data/5_TMS_HUBS_METADATA_FILTERED.pickle
senepy/data/5_TMS_SIGS_DICTIONARY_FILTERED.pickle
senepy/data/5_TMS_SIGS_METADATA_FILTERED.pickle
senepy/data/6_HUMAN_HUBS_DICTIONARY_FILTERED.pickle
senepy/data/6_HUMAN_HUBS_METADATA_FILTERED.pickle
senepy/data/6_HUMAN_SIGS_DICTIONARY_FILTERED.pickle
senepy/data/6_HUMAN_SIGS_METADATA_FILTERED.pickle
senepy/data/Human_literature_markers.pickle
senepy/data/Mouse_literature_markers.pickle
senepy/data/R1_6_HUMAN_HUBS_DICTIONARY_FILTERED.pickle
senepy/data/R1_6_HUMAN_HUBS_METADATA_FILTERED.pickle
senepy/data/R1_6_HUMAN_SIGS_DICTIONARY_FILTERED.pickle
senepy/data/R1_6_HUMAN_SIGS_METADATA_FILTERED.pickle
senepy/data/R1_TMS_HUBS_DICTIONARY_FILTERED.pickle
senepy/data/R1_TMS_HUBS_METADATA_FILTERED.pickle
senepy/data/R1_TMS_SIGS_DICTIONARY_FILTERED.pickle
senepy/data/R1_TMS_SIGS_METADATA_FILTERED.pickle
senepy/data/mart_export.txt
senepy/data/senGPT.txt
senepy-1.0.0.dist-info/LICENSE
senepy-1.0.0.dist-info/METADATA
senepy-1.0.0.dist-info/WHEEL
senepy-1.0.0.dist-info/top_level.txt
senepy-1.0.0.dist-info/RECORD
