Metadata-Version: 2.1
Name: senepy
Version: 1.0.0
Summary: tools to score single-cells based on senescence marker expression
Author-email: Mark Sanborn <mark.email24@gmail.com>
Project-URL: Homepage, https://github.com/mousepixels/senepy
Project-URL: Bug Tracker, https://github.com/mousepixels/senepy
Classifier: Programming Language :: Python :: 3
Classifier: License :: OSI Approved :: MIT License
Classifier: Operating System :: OS Independent
Requires-Python: >=3.7
License-File: LICENSE
Requires-Dist: pandas >=1.0
Requires-Dist: numpy >=1.17.0
Requires-Dist: tqdm
Requires-Dist: sympy >=1.12
Provides-Extra: scdrs
Requires-Dist: scdrs ==1.0.2 ; extra == 'scdrs'
